modularl/__init__.py
modularl/agents/__init__.py
modularl/agents/agent.py
modularl/agents/ddpg.py
modularl/agents/sac.py
modularl/agents/td3.py
modularl/policies/__init__.py
modularl/policies/deterministic_policy.py
modularl/policies/gaussian_policy.py
modularl/policies/policy.py
modularl/q_functions/__init__.py
modularl/q_functions/q_functions.py
modularl/q_functions/state_action_q_function.py
modularl/replay_buffers/__init__.py
modularl/replay_buffers/base_buffer.py
modularl/replay_buffers/replay_buffer.py
modularl/utils/__init__.py
tests/__init__.py
modularl-0.1.5.dist-info/LICENSE
modularl-0.1.5.dist-info/METADATA
modularl-0.1.5.dist-info/WHEEL
modularl-0.1.5.dist-info/top_level.txt
modularl-0.1.5.dist-info/RECORD
