Metadata-Version: 2.1
Name: modularl
Version: 0.1.5
Summary: A modular reinforcement learning library
Home-page: https://github.com/zakaria-narjis/modularl
Author: Zakaria Narjis
Author-email: zakaria.narjis.97@gmail.com
Classifier: Development Status :: 4 - Beta
Classifier: Intended Audience :: Developers
Classifier: Intended Audience :: Science/Research
Classifier: License :: OSI Approved :: MIT License
Classifier: Programming Language :: Python :: 3
Classifier: Programming Language :: Python :: 3.7
Classifier: Programming Language :: Python :: 3.8
Classifier: Programming Language :: Python :: 3.9
Classifier: Programming Language :: Python :: 3.10
Classifier: Programming Language :: Python :: 3.11
Classifier: Operating System :: OS Independent
Classifier: Topic :: Scientific/Engineering :: Artificial Intelligence
Requires-Python: >=3.7
License-File: LICENSE
Requires-Dist: numpy >=1.24
Requires-Dist: torch >=2.0
Requires-Dist: torchrl >=0.4.0
Requires-Dist: tensorboard >=2.17.0
Provides-Extra: dev
Requires-Dist: black ; extra == 'dev'
Requires-Dist: flake8 ; extra == 'dev'
Requires-Dist: mypy ; extra == 'dev'
Requires-Dist: pytest >=6.2.5 ; extra == 'dev'
